<!-- 
  Skins
-->

<ModOps>

    <!-- START WINDJAMMER SKINS -->
    <ModOp GUID='80147' Type="addNextSibling">
        <Asset>
            <Template>Skin</Template>
            <Values>
                <Standard>
                    <GUID>1742100626</GUID>
                    <Name>Windjammer Skin 01</Name>
                    <IconFilename>data/graphics/icons/icon_windjammer_skin_01.png</IconFilename>
                </Standard>
                <Skin>
                    <SkinName>1742100626</SkinName>
                    <SkinVariations>
                        <Item>
                            <FileName>data/graphics/vehicle/windjammer/windjammer_skin_01.cfg</FileName>
                        </Item>
                    </SkinVariations>
                </Skin>
                <Locked>
                    <DefaultLockedState>0</DefaultLockedState>
                </Locked>
            </Values>
        </Asset>
        <Asset>
            <Template>Skin</Template>
            <Values>
                <Standard>
                    <GUID>1742100627</GUID>
                    <Name>Windjammer Skin 03</Name>
                    <IconFilename>data/graphics/icons/icon_windjammer_skin_02.png</IconFilename>
                </Standard>
                <Skin>
                    <SkinName>1742100627</SkinName>
                    <SkinVariations>
                        <Item>
                            <FileName>data/graphics/vehicle/windjammer/windjammer_skin_02.cfg</FileName>
                        </Item>
                    </SkinVariations>
                </Skin>
                <Locked>
                    <DefaultLockedState>0</DefaultLockedState>
                </Locked>
            </Values>
        </Asset>
        <Asset>
            <Template>Skin</Template>
            <Values>
                <Standard>
                    <GUID>1742100628</GUID>
                    <Name>Windjammer Skin 02</Name>
                    <IconFilename>data/graphics/icons/icon_windjammer_skin_03.png</IconFilename>
                </Standard>
                <Skin>
                    <SkinName>1742100628</SkinName>
                    <SkinVariations>
                        <Item>
                            <FileName>data/graphics/vehicle/windjammer/windjammer_skin_03.cfg</FileName>
                        </Item>
                    </SkinVariations>
                </Skin>
                <Locked>
                    <DefaultLockedState>0</DefaultLockedState>
                </Locked>
            </Values>
        </Asset>
    </ModOp>
    <!-- END WINDJAMMER SKINS -->

    <!-- START THE DUKE SKINS -->
    <ModOp GUID='80147' Type="addNextSibling">
        <Asset>
            <Template>Skin</Template>
            <Values>
                <Standard>
                    <GUID>1742100666</GUID>
                    <Name>The Duke Skin 01</Name>
                    <IconFilename>data/graphics/icons/icon_theduke_skin_01.png</IconFilename>
                </Standard>
                <Skin>
                    <SkinName>1742100666</SkinName>
                    <SkinVariations>
                        <Item>
                            <FileName>data/graphics/vehicle/man_of_war_duke/man_of_war_duke_skin_01.cfg</FileName>
                        </Item>
                    </SkinVariations>
                </Skin>
                <Locked>
                    <DefaultLockedState>0</DefaultLockedState>
                </Locked>
            </Values>
        </Asset>
        <Asset>
            <Template>Skin</Template>
            <Values>
                <Standard>
                    <GUID>1742100667</GUID>
                    <Name>The Duke Skin 02</Name>
                    <IconFilename>data/graphics/icons/icon_theduke_skin_02.png</IconFilename>
                </Standard>
                <Skin>
                    <SkinName>1742100667</SkinName>
                    <SkinVariations>
                        <Item>
                            <FileName>data/graphics/vehicle/man_of_war_duke/man_of_war_duke_skin_02.cfg</FileName>
                        </Item>
                    </SkinVariations>
                </Skin>
                <Locked>
                    <DefaultLockedState>0</DefaultLockedState>
                </Locked>
            </Values>
        </Asset>
    </ModOp>
    <!-- END THE DUKE SKINS -->

    <!-- START SMALL CARGO SHIP SKINS -->
    <ModOp GUID='80147' Type="addNextSibling">
        <Asset>
            <Template>Skin</Template>
            <Values>
                <Standard>
                    <GUID>1742100668</GUID>
                    <Name>Small Cargo Ship Skin 01</Name>
                    <IconFilename>data/graphics/icons/icon_small_cargo_ship_skin_01.png</IconFilename>
                </Standard>
                <Skin>
                    <SkinName>1742100668</SkinName>
                    <SkinVariations>
                        <Item>
                            <FileName>data/graphics/vehicle/small_cargo_ship/small_cargo_ship_skin_01.cfg</FileName>
                        </Item>
                    </SkinVariations>
                </Skin>
                <Locked>
                    <DefaultLockedState>0</DefaultLockedState>
                </Locked>
            </Values>
        </Asset>
        <Asset>
            <Template>Skin</Template>
            <Values>
                <Standard>
                    <GUID>1742100669</GUID>
                    <Name>Small Cargo Ship Skin 01</Name>
                    <IconFilename>data/graphics/icons/icon_small_cargo_ship_skin_02.png</IconFilename>
                </Standard>
                <Skin>
                    <SkinName>1742100669</SkinName>
                    <SkinVariations>
                        <Item>
                            <FileName>data/graphics/vehicle/small_cargo_ship/small_cargo_ship_skin_02.cfg</FileName>
                        </Item>
                    </SkinVariations>
                </Skin>
                <Locked>
                    <DefaultLockedState>0</DefaultLockedState>
                </Locked>
            </Values>
        </Asset>
        <Asset>
            <Template>Skin</Template>
            <Values>
                <Standard>
                    <GUID>1742100670</GUID>
                    <Name>Small Cargo Ship Skin 03</Name>
                    <IconFilename>data/graphics/icons/icon_small_cargo_ship_skin_03.png</IconFilename>
                </Standard>
                <Skin>
                    <SkinName>1742100670</SkinName>
                    <SkinVariations>
                        <Item>
                            <FileName>data/graphics/vehicle/small_cargo_ship/small_cargo_ship_skin_03.cfg</FileName>
                        </Item>
                    </SkinVariations>
                </Skin>
                <Locked>
                    <DefaultLockedState>0</DefaultLockedState>
                </Locked>
            </Values>
        </Asset>
        <Asset>
            <Template>Skin</Template>
            <Values>
                <Standard>
                    <GUID>1742100671</GUID>
                    <Name>Small Cargo Ship Skin 04</Name>
                    <IconFilename>data/graphics/icons/icon_small_cargo_ship_skin_04.png</IconFilename>
                </Standard>
                <Skin>
                    <SkinName>1742100671</SkinName>
                    <SkinVariations>
                        <Item>
                            <FileName>data/graphics/vehicle/small_cargo_ship/small_cargo_ship_skin_04.cfg</FileName>
                        </Item>
                    </SkinVariations>
                </Skin>
                <Locked>
                    <DefaultLockedState>0</DefaultLockedState>
                </Locked>
            </Values>
        </Asset>
    </ModOp>
    <!-- END SMALL CARGO SHIP SKINS -->

    <!-- START SMALL BATTLE CRUISER SKINS -->
    <ModOp GUID='80147' Type="addNextSibling">
        <Asset>
            <Template>Skin</Template>
            <Values>
                <Standard>
                    <GUID>1742100672</GUID>
                    <Name>Small Battle Cruiser Skin 01</Name>
                    <IconFilename>data/graphics/icons/icon_small_battlecruiser_skin_01.png</IconFilename>
                </Standard>
                <Skin>
                    <SkinName>1742100672</SkinName>
                    <SkinVariations>
                        <Item>
                            <FileName>data/graphics/vehicle/small_battle_cruiser/small_battle_cruiser_skin_01.cfg</FileName>
                        </Item>
                    </SkinVariations>
                </Skin>
                <Locked>
                    <DefaultLockedState>0</DefaultLockedState>
                </Locked>
            </Values>
        </Asset>
        <Asset>
            <Template>Skin</Template>
            <Values>
                <Standard>
                    <GUID>1742100673</GUID>
                    <Name>Small Battle Cruiser Skin 02</Name>
                    <IconFilename>data/graphics/icons/icon_small_battlecruiser_skin_02.png</IconFilename>
                </Standard>
                <Skin>
                    <SkinName>1742100673</SkinName>
                    <SkinVariations>
                        <Item>
                            <FileName>data/graphics/vehicle/small_battle_cruiser/small_battle_cruiser_skin_02.cfg</FileName>
                        </Item>
                    </SkinVariations>
                </Skin>
                <Locked>
                    <DefaultLockedState>0</DefaultLockedState>
                </Locked>
            </Values>
        </Asset>
        <Asset>
            <Template>Skin</Template>
            <Values>
                <Standard>
                    <GUID>1742100674</GUID>
                    <Name>Small Battle Cruiser Skin 03</Name>
                    <IconFilename>data/graphics/icons/icon_small_battlecruiser_skin_03.png</IconFilename>
                </Standard>
                <Skin>
                    <SkinName>1742100674</SkinName>
                    <SkinVariations>
                        <Item>
                            <FileName>data/graphics/vehicle/small_battle_cruiser/small_battle_cruiser_skin_03.cfg</FileName>
                        </Item>
                    </SkinVariations>
                </Skin>
                <Locked>
                    <DefaultLockedState>0</DefaultLockedState>
                </Locked>
            </Values>
        </Asset>
        <Asset>
            <Template>Skin</Template>
            <Values>
                <Standard>
                    <GUID>1742100675</GUID>
                    <Name>Small Battle Cruiser Skin 04</Name>
                    <IconFilename>data/graphics/icons/icon_small_battlecruiser_skin_04.png</IconFilename>
                </Standard>
                <Skin>
                    <SkinName>1742100675</SkinName>
                    <SkinVariations>
                        <Item>
                            <FileName>data/graphics/vehicle/small_battle_cruiser/small_battle_cruiser_skin_04.cfg</FileName>
                        </Item>
                    </SkinVariations>
                </Skin>
                <Locked>
                    <DefaultLockedState>0</DefaultLockedState>
                </Locked>
            </Values>
        </Asset>
        <Asset>
            <Template>Skin</Template>
            <Values>
                <Standard>
                    <GUID>1742100676</GUID>
                    <Name>Small Battle Cruiser Skin 05</Name>
                    <IconFilename>data/graphics/icons/icon_small_battlecruiser_skin_05.png</IconFilename>
                </Standard>
                <Skin>
                    <SkinName>1742100676</SkinName>
                    <SkinVariations>
                        <Item>
                            <FileName>data/graphics/vehicle/small_battle_cruiser/small_battle_cruiser_skin_05.cfg</FileName>
                        </Item>
                    </SkinVariations>
                </Skin>
                <Locked>
                    <DefaultLockedState>0</DefaultLockedState>
                </Locked>
            </Values>
        </Asset>
    </ModOp>
    <!-- END SMALL BATTLE CRUISER SKINS -->

    <!-- START HEAVY BATTLE CRUISER SKINS -->
    <ModOp GUID='80147' Type="addNextSibling">
        <Asset>
            <Template>Skin</Template>
            <Values>
                <Standard>
                    <GUID>1742100677</GUID>
                    <Name>Heavy Battle Cruiser Skin 01</Name>
                    <IconFilename>data/graphics/icons/icon_heavy_battlecruiser_skin_01.png</IconFilename>
                </Standard>
                <Skin>
                    <SkinName>1742100677</SkinName>
                    <SkinVariations>
                        <Item>
                            <FileName>data/graphics/vehicle/heavy_battle_cruiser/heavy_battle_cruiser_skin_01.cfg</FileName>
                        </Item>
                    </SkinVariations>
                </Skin>
                <Locked>
                    <DefaultLockedState>0</DefaultLockedState>
                </Locked>
            </Values>
        </Asset>
        <Asset>
            <Template>Skin</Template>
            <Values>
                <Standard>
                    <GUID>1742100678</GUID>
                    <Name>Heavy Battle Cruiser Skin 02</Name>
                    <IconFilename>data/graphics/icons/icon_heavy_battlecruiser_skin_02.png</IconFilename>
                </Standard>
                <Skin>
                    <SkinName>1742100678</SkinName>
                    <SkinVariations>
                        <Item>
                            <FileName>data/graphics/vehicle/heavy_battle_cruiser/heavy_battle_cruiser_skin_02.cfg</FileName>
                        </Item>
                    </SkinVariations>
                </Skin>
                <Locked>
                    <DefaultLockedState>0</DefaultLockedState>
                </Locked>
            </Values>
        </Asset>
        <Asset>
            <Template>Skin</Template>
            <Values>
                <Standard>
                    <GUID>1742100679</GUID>
                    <Name>Heavy Battle Cruiser Skin 03</Name>
                    <IconFilename>data/graphics/icons/icon_heavy_battlecruiser_skin_03.png</IconFilename>
                </Standard>
                <Skin>
                    <SkinName>1742100679</SkinName>
                    <SkinVariations>
                        <Item>
                            <FileName>data/graphics/vehicle/heavy_battle_cruiser/heavy_battle_cruiser_skin_03.cfg</FileName>
                        </Item>
                    </SkinVariations>
                </Skin>
                <Locked>
                    <DefaultLockedState>0</DefaultLockedState>
                </Locked>
            </Values>
        </Asset>
        <Asset>
            <Template>Skin</Template>
            <Values>
                <Standard>
                    <GUID>1742100680</GUID>
                    <Name>Heavy Battle Cruiser Skin 04</Name>
                    <IconFilename>data/graphics/icons/icon_heavy_battlecruiser_skin_04.png</IconFilename>
                </Standard>
                <Skin>
                    <SkinName>1742100680</SkinName>
                    <SkinVariations>
                        <Item>
                            <FileName>data/graphics/vehicle/heavy_battle_cruiser/heavy_battle_cruiser_skin_04.cfg</FileName>
                        </Item>
                    </SkinVariations>
                </Skin>
                <Locked>
                    <DefaultLockedState>0</DefaultLockedState>
                </Locked>
            </Values>
        </Asset>
        <Asset>
            <Template>Skin</Template>
            <Values>
                <Standard>
                    <GUID>1742100681</GUID>
                    <Name>Heavy Battle Cruiser Skin 05</Name>
                    <IconFilename>data/graphics/icons/icon_heavy_battlecruiser_skin_05.png</IconFilename>
                </Standard>
                <Skin>
                    <SkinName>1742100681</SkinName>
                    <SkinVariations>
                        <Item>
                            <FileName>data/graphics/vehicle/heavy_battle_cruiser/heavy_battle_cruiser_skin_05.cfg</FileName>
                        </Item>
                    </SkinVariations>
                </Skin>
                <Locked>
                    <DefaultLockedState>0</DefaultLockedState>
                </Locked>
            </Values>
        </Asset>
    </ModOp>
    <!-- END HEAVY BATTLE CRUISER SKINS -->

    <!-- START SMALL OIL TANKER SKINS -->
    <ModOp GUID='80147' Type="addNextSibling">
        <Asset>
            <Template>Skin</Template>
            <Values>
                <Standard>
                    <GUID>1742100682</GUID>
                    <Name>Small Oil Tanker Skin 01</Name>
                    <IconFilename>data/graphics/icons/icon_small_oil_tanker_skin_01.png</IconFilename>
                </Standard>
                <Skin>
                    <SkinName>1742100682</SkinName>
                    <SkinVariations>
                        <Item>
                            <FileName>data/graphics/vehicle/small_oil_tanker/small_oil_tanker_02.cfg</FileName>
                        </Item>
                    </SkinVariations>
                </Skin>
                <Locked>
                    <DefaultLockedState>0</DefaultLockedState>
                </Locked>
            </Values>
        </Asset>
        <Asset>
            <Template>Skin</Template>
            <Values>
                <Standard>
                    <GUID>1742100683</GUID>
                    <Name>Small Oil Tanker Skin 02</Name>
                    <IconFilename>data/graphics/icons/icon_small_oil_tanker_skin_02.png</IconFilename>
                </Standard>
                <Skin>
                    <SkinName>1742100683</SkinName>
                    <SkinVariations>
                        <Item>
                            <FileName>data/graphics/vehicle/small_oil_tanker/small_oil_tanker_03.cfg</FileName>
                        </Item>
                    </SkinVariations>
                </Skin>
                <Locked>
                    <DefaultLockedState>0</DefaultLockedState>
                </Locked>
            </Values>
        </Asset>
    </ModOp>
    <!-- END SMALL OIL TANKER SKINS -->

    <!-- START OIL TANKER SKINS -->
    <ModOp GUID='80147' Type="addNextSibling">
        <Asset>
            <Template>Skin</Template>
            <Values>
                <Standard>
                    <GUID>1742100684</GUID>
                    <Name>Oil Tanker Skin 01</Name>
                    <IconFilename>data/graphics/icons/icon_oil_tanker_skin_01.png</IconFilename>
                </Standard>
                <Skin>
                    <SkinName>1742100684</SkinName>
                    <SkinVariations>
                        <Item>
                            <FileName>data/graphics/vehicle/oil_tanker/oil_tanker_02.cfg</FileName>
                        </Item>
                    </SkinVariations>
                </Skin>
                <Locked>
                    <DefaultLockedState>0</DefaultLockedState>
                </Locked>
            </Values>
        </Asset>
        <Asset>
            <Template>Skin</Template>
            <Values>
                <Standard>
                    <GUID>1742100685</GUID>
                    <Name>Oil Tanker Skin 02</Name>
                    <IconFilename>data/graphics/icons/icon_oil_tanker_skin_02.png</IconFilename>
                </Standard>
                <Skin>
                    <SkinName>1742100685</SkinName>
                    <SkinVariations>
                        <Item>
                            <FileName>data/graphics/vehicle/oil_tanker/oil_tanker_03.cfg</FileName>
                        </Item>
                    </SkinVariations>
                </Skin>
                <Locked>
                    <DefaultLockedState>0</DefaultLockedState>
                </Locked>
            </Values>
        </Asset>
    </ModOp>
    <!-- END OIL TANKER SKINS -->

    <!-- START LARGE OIL TANKER SKINS -->
    <ModOp GUID='80147' Type="addNextSibling">
        <Asset>
            <Template>Skin</Template>
            <Values>
                <Standard>
                    <GUID>1742100686</GUID>
                    <Name>Large Oil Tanker Skin 01</Name>
                    <IconFilename>data/graphics/icons/icon_large_oil_tanker_skin_01.png</IconFilename>
                </Standard>
                <Skin>
                    <SkinName>1742100686</SkinName>
                    <SkinVariations>
                        <Item>
                            <FileName>data/graphics/vehicle/large_oil_tanker/large_oil_tanker_02.cfg</FileName>
                        </Item>
                    </SkinVariations>
                </Skin>
                <Locked>
                    <DefaultLockedState>0</DefaultLockedState>
                </Locked>
            </Values>
        </Asset>
        <Asset>
            <Template>Skin</Template>
            <Values>
                <Standard>
                    <GUID>1742100687</GUID>
                    <Name>Large Oil Tanker Skin 02</Name>
                    <IconFilename>data/graphics/icons/icon_large_oil_tanker_skin_02.png</IconFilename>
                </Standard>
                <Skin>
                    <SkinName>1742100687</SkinName>
                    <SkinVariations>
                        <Item>
                            <FileName>data/graphics/vehicle/large_oil_tanker/large_oil_tanker_03.cfg</FileName>
                        </Item>
                    </SkinVariations>
                </Skin>
                <Locked>
                    <DefaultLockedState>0</DefaultLockedState>
                </Locked>
            </Values>
        </Asset>
    </ModOp>
    <!-- END LARGE OIL TANKER SKINS -->

</ModOps>