<?xml version="1.0"?>
<ModOps>
  <ModOp Type="add" Path="/TextExport/Texts">
    <Text>
      <GUID>1742110098</GUID>      <!--  Flute - Product -->
      <Text>长笛</Text>
    </Text>
    <Text>
      <GUID>1742110099</GUID>      <!-- Flute - Product - Description -->
      <Text>用于演奏一些基本曲调的基本长笛。</Text>
    </Text>
    <Text>
      <GUID>1742110123</GUID>      <!--  Artisan's Workshop: Flute - Building -->
      <Text>工匠的工作坊： 长笛</Text>
    </Text>
    <Text>
      <GUID>1742110124</GUID>      <!--  Artisan's Workshop: Flute DUMMY - Building -->
      <Text>工匠的工作坊： 长笛 (DUMMY)</Text>
    </Text>
    <Text>
      <GUID>1742110101</GUID>      <!--  Artisan's Workshop: Flute - Building - Description -->
      <Text>为普通人制作一些基本的长笛。</Text>
    </Text>
    <Text>
      <GUID>1742110125</GUID>      <!--  Flute - ProductionChain -->
      <Text>长笛</Text>
    </Text>
    <Text>
      <GUID>1742110105</GUID>      <!-- Flute - ProductionChain - Description -->
      <Text>用此产业链制作长笛。</Text>
    </Text>
  </ModOp>
</ModOps>