<?xml version="1.0"?>
<ModOps>
  <ModOp Type="add" Path="/TextExport/Texts">
    <Text>
      <GUID>100783</GUID>      <!-- Small Oil Harbour - Text -->
      <Text>Small Strategic Harbour</Text>
    </Text>
    <Text>
      <GUID>101329</GUID>      <!-- Small Oil Harbour (NW) - Text -->
      <Text>Small Strategic Harbour</Text>
    </Text>
    <Text>
      <GUID>119031</GUID>      <!-- Small Oil Harbour (EN) - Text -->
      <Text>Small Strategic Harbour</Text>
    </Text>
    <Text>
      <GUID>101403</GUID>      <!-- Medium Oil Harbour - Text -->
      <Text>Medium Strategic Harbour</Text>
    </Text>
    <Text>
      <GUID>101405</GUID>      <!-- Medium Oil Harbour (NW) - Text -->
      <Text>Medium Strategic Harbour</Text>
    </Text>
    <Text>
      <GUID>119032</GUID>      <!-- Medium Oil Harbour (EN) - Text -->
      <Text>Medium Strategic Harbour</Text>
    </Text>
    <Text>
      <GUID>101404</GUID>      <!-- Large Oil Harbour - Text -->
      <Text>Large Strategic Harbour</Text>
    </Text>
    <Text>
      <GUID>101406</GUID>      <!-- Large Oil Harbour (NW) - Text -->
      <Text>Large Strategic Harbour</Text>
    </Text>
    <Text>
      <GUID>119033</GUID>      <!-- Large Oil Harbour (EN) - Text -->
      <Text>Large Strategic Harbour</Text>
    </Text>
    <Text>
      <GUID>119259</GUID>      <!-- Grand Oil Harbour - Text -->
      <Text>Grand Strategic Harbour</Text>
    </Text>
    <Text>
      <GUID>119281</GUID>      <!-- Grand Oil Harbour (NW) - Text -->
      <Text>Grand Strategic Harbour</Text>
    </Text>
    <Text>
      <GUID>270172</GUID>      <!-- Grand Oil Harbour (EN) - Text -->
      <Text>Grand Strategic Harbour</Text>
    </Text>
    <Text>
      <GUID>10951</GUID>      <!-- Oil Harbor Infocorner - Text -->
      <Text>Central harbour for strategic goods. Place where trains are used as transportation of strategic goods on the island. Switch to Train UI with SHIFT+C to check trains and upgrade the building.</Text>
    </Text>
    <Text>
      <GUID>11717</GUID>      <!-- Strategic Routes - Text -->
      <Text>Strategic Routes</Text>
    </Text>
    <Text>
      <GUID>11887</GUID>      <!-- Oil Route Description Text - Text -->
      <Text>Create routes to ship strategic goods between your harbours.</Text>
    </Text>
    <Text>
      <GUID>25530</GUID>      <!-- RouteDescription_OilRoute - Text -->
      <Text>Use special ships to distribute strategic goods between the harbours of islands you control.</Text>
    </Text>
    <Text>
      <GUID>5628</GUID>      <!-- Strategic Routes - Text -->
      <Text>Strategic Routes</Text>
    </Text>
    <Text>
      <GUID>19153</GUID>      <!-- Strategic Routes 2 - Text -->
      <Text>Create Strategic Route</Text>
    </Text>
    <Text>
      <GUID>1742004555</GUID>      <!-- Strategic Harbour (AR) - Building -->
      <Text>Strategic Harbour</Text>
    </Text>
    <Text>
      <GUID>1742004281</GUID>      <!-- Strategic Pier (AR) - Building -->
      <Text>Strategic Pier</Text>
    </Text>
    <Text>
      <GUID>1742004392</GUID>      <!-- Strategic Pier (OW) - Building -->
      <Text>Strategic Pier</Text>
    </Text>
    <Text>
      <GUID>1742004393</GUID>      <!-- Strategic Pier (NW) - Building -->
      <Text>Strategic Pier</Text>
    </Text>
    <Text>
      <GUID>1742004454</GUID>      <!-- Strategic Pier (EN) - Building -->
      <Text>Strategic Pier</Text>
    </Text>
    <Text>
      <GUID>1742004282</GUID>      <!-- Strategic Pier - Building - Description -->
      <Text>Load and unload strategic goods here. Strategic goods are goods only be possible to transport with special ships. Like Oil and Ice Blocks.</Text>
    </Text>
  </ModOp>
</ModOps>