<?xml version="1.0"?>
<ModOps>
    <ModOp Type="add" Path="/TextExport/Texts">
        <Text>
            <GUID>1742110003</GUID>            <!--  Artisan's Workshop: Saxophone - Building -->
            <Text>Мастерская ремесленника: Саксофоны</Text>
        </Text>
        <Text>
            <GUID>1742110004</GUID>            <!--  Artisan's Workshop: Saxophone - Building - Description -->
            <Text>Думаете я потрясающий саксофонист? Но я их только произвожу...</Text>
        </Text>
        <Text>
            <GUID>1742110005</GUID>            <!--  Artisan's Workshop: Harp - Building -->
            <Text>Мастерская ремесленника: Арфы</Text>
        </Text>
        <Text>
            <GUID>1742110006</GUID>            <!--  Artisan's Workshop: Harp - Building - Description -->
            <Text>Арфы — это элегантные инструменты, на которых играют люди или ангелы.</Text>
        </Text>
        <Text>
            <GUID>1742110007</GUID>            <!--  Artisan's Workshop: Piano - Building -->
            <Text>Мастерская ремесленника: Фортепиано</Text>
        </Text>
        <Text>
            <GUID>1742110008</GUID>            <!--  Artisan's Workshop: Piano - Building - Description -->
            <Text>Фортепиано и само по себе является произведением искусства.</Text>
        </Text>
        <Text>
            <GUID>1742110009</GUID>            <!--  Workshop: Guitar - Building -->
            <Text>Мастерская: Гитары</Text>
        </Text>
        <Text>
            <GUID>1742110010</GUID>            <!--  Workshop: Guitar - Building - Description -->
            <Text>Мы тут производим гитары, а не играем на них!</Text>
        </Text>
        <Text>
            <GUID>1742110011</GUID>            <!--  Workshop: Banjo - Building -->
            <Text>Мастерская: Банджо</Text>
        </Text>
        <Text>
            <GUID>1742110012</GUID>            <!--  Workshop: Banjo - Building - Description -->
            <Text>Хей! Я тут делаю классные банджо!</Text>
        </Text>
        <Text>
            <GUID>1742110013</GUID>            <!--  Qilaut Maker - Building -->
            <Text>Изготовитель Килаутов</Text>
        </Text>
        <Text>
            <GUID>1742110014</GUID>            <!--  Qilaut Maker - Building - Description -->
            <Text>Бам-бам-бам! Пусть на этих килаутах продолжают играть!</Text>
        </Text>
        <Text>
            <GUID>1742110015</GUID>            <!--  Workshop: Blank - Building -->
            <Text>Мастерская: Пусто</Text>
        </Text>
        <Text>
            <GUID>1742110016</GUID>            <!--  Workshop: Blank - Building - Description -->
            <Text>Какой инструмент нам следует производить в Новом Свете?</Text>
        </Text>
        <Text>
            <GUID>1742110019</GUID>            <!--  Saxophone - Product -->
            <Text>Саксофоны</Text>
        </Text>
        <Text>
            <GUID>1742110020</GUID>            <!-- Saxophone - Product - Description -->
            <Text>Первоклассный тростевой инструмент, сделанный исключительно из латуни, который покоряет сердца своим волнующим звучанием!</Text>
        </Text>
        <Text>
            <GUID>1742110021</GUID>            <!--  Harp - Product -->
            <Text>Арфы</Text>
        </Text>
        <Text>
            <GUID>1742110022</GUID>            <!-- Harp - Product - Description -->
            <Text>Поистине ангельский музыкальный инструмент, который делают с применением вишневого дерева, стали и золота. Этот щипковый музыкальный инструмент состоит из двух расположенных под углом рам, между которыми натянуто множество струн. Его звуки просто завораживают.</Text>
        </Text>
        <Text>
            <GUID>1742110023</GUID>            <!--  Piano - Product -->
            <Text>Фортепиано</Text>
        </Text>
        <Text>
            <GUID>1742110024</GUID>            <!-- Piano - Product - Description -->
            <Text>Сложнейший музыкальный инструмент, изготовляемый из лучших пород вишневого дерева, целлулоида, стали и лака. Качественные и благозвучные, но чрезвычайно дорогостоящие образцы могли позволить иметь себе лишь особы королевского двора, что отражается в названии "Рояль".</Text>
        </Text>
        <Text>
            <GUID>1742110025</GUID>            <!--  Guitar - Product -->
            <Text>Гитары</Text>
        </Text>
        <Text>
            <GUID>1742110026</GUID>            <!-- Guitar - Product - Description -->
            <Text>Инструмент, на котором любой хотел бы сыграть, изготавливается из высококачественной шпонированной древесины, стали и лака. Популярность гитар бьёт все рекорды!</Text>
        </Text>
        <Text>
            <GUID>1742110027</GUID>            <!--  Banjo - Product -->
            <Text>Банджо</Text>
        </Text>
        <Text>
            <GUID>1742110028</GUID>            <!-- Banjo - Product - Description -->
            <Text>Задорный инструмент, сделанный  из деревянного шпона и стали, который раньше делали из высушенной тыквы с натянутой на неё кожей. Из инструмента льётся яркая и звонкая музыка с четким, заводным ритмом.</Text>
        </Text>
        <Text>
            <GUID>1742110033</GUID>            <!--  Hides from caribou for Qilaut - GuildhouseBuff -->
            <Text>Шкуры карибу для Килаута</Text>
        </Text>
        <Text>
            <GUID>1742110034</GUID>            <!-- Hides from caribou for Qilaut - GuildhouseBuff - Description -->
            <Text>Шкуры карибу применяются для изготовления Килаута.</Text>
        </Text>
        <Text>
            <GUID>1742110037</GUID>            <!--  Qilaut - ProductionChain -->
            <Text>Килаут</Text>
        </Text>
        <Text>
            <GUID>1742110038</GUID>            <!-- Qilaut - ProductionChain - Description -->
            <Text>Необычный Килаут делают шкур Карибу и дерева. Килаут состоит из деревянной рамы с ручкой, поверх которой натянута кожа. Для игры на барабане использовался катуак – барабанная палочка, которая обычно изготавливалась из оленьих рогов, ею ударяли по деревянной раме, тем самым производя высокий звук, который резонировал в коже. Исполнитель обычно одновременно пел и танцевал.</Text>
        </Text>
        <Text>
            <GUID>1742110039</GUID>            <!--  Saxophone - Recipe -->
            <Text>Саксофон</Text>
        </Text>
        <Text>
            <GUID>1742110040</GUID>            <!-- Saxophone - Recipe - Description -->
            <Text>Саксофон - это единственный в мире инструмент, производящийся из изогнутой латуни. Типичный саксофон изготавливается в 8 вариантах - сопраниссимо, сопранино, сопрано, альт, тенор, баритон, бас и контрабас. Саксофон можно разделить на 3 главных элемента: корпус, раструб, тонкая трубка, на которую насаживается мундштук, являющийся малой частью инструмента. Основные этапы производства включают в себя формирование деталей, их сборку и окончательную полировку.</Text>
        </Text>
        <Text>
            <GUID>1742110041</GUID>            <!--  Harp - Recipe -->
            <Text>Арфы</Text>
        </Text>
        <Text>
            <GUID>1742110042</GUID>            <!-- Harp - Recipe - Description -->
            <Text>В производстве арф всё начинается с древесины, которая отстаивается годами. Затем идёт склейка, обточка и сборка. Собирается каркас корпуса, обшивка, после чего начинается подгонка. С одной стороны – всё делается по чертежам, строгим нормативам, а с другой - каждый инструмент индивидуален и звучит по-своему. Это ремесло, где ничего не повторяется и двух одинаковых арф нет. Скоро эти заготовки станут роскошными арфами!</Text>
        </Text>
        <Text>
            <GUID>1742110043</GUID>            <!--  Piano - Recipe -->
            <Text>Фортепиано</Text>
        </Text>
        <Text>
            <GUID>1742110044</GUID>            <!-- Piano - Recipe - Description -->
            <Text>Дерево, которое звучит! Нет ни одного инструмента, который в истории музыки имел бы настолько сильное влияние на целые эпохи, как фортепиано. Сорта твердой древесины используют для изготовления футора (остов корпуса), вирбельбанка (колковой доски), постелей дек, и различных частей механики. Упругие и эластичные сорта древесины используются для изготовления резонансных дек, клавиш, штульрам и клавиатурных рам. Чугунная рама - важнейшая составная часть, выдерживающая на себе суммарное натяжение струн, которое может превышать 20 тонн. В сложнейшем процессе создания фортепиано используются до 12 000 частей и деталей!</Text>
        </Text>
        <Text>
            <GUID>1742110045</GUID>            <!--  Guitar - Recipe -->
            <Text>Гитары</Text>
        </Text>
        <Text>
            <GUID>1742110046</GUID>            <!-- Guitar - Recipe - Description -->
            <Text>Здесь используется шпон только самого высокого качества! Древесина с сучками и трещинками сразу отбраковываются. Происходит просушка, потом кроят верхнюю и нижнюю деки и прессуют шпон в блок для последующего изготовления гитарного грифа. Далее блок разрезают, собирают и шлифуют и лакируют. После чего всё соединят вместе, устанавливают колковый механизм и натягивают струны.</Text>
        </Text>
        <Text>
            <GUID>1742110047</GUID>            <!--  Banjo - Recipe -->
            <Text>Банджо</Text>
        </Text>
        <Text>
            <GUID>1742110048</GUID>            <!-- Banjo - Recipe - Description -->
            <Text>Банджо - задорный инструмент, сделанный  из деревянного шпона и стали, который раньше делали из высушенной тыквы с натянутой на неё кожей. Из инструмента льётся яркая и звонкая музыка с четким, заводным ритмом.</Text>
        </Text>
        <Text>
            <GUID>1742110049</GUID>            <!--  Workshop - RecipeList -->
            <Text>Мастерская</Text>
        </Text>
        <Text>
            <GUID>1742110050</GUID>            <!-- Workshop - RecipeList - Description -->
            <Text>Мастерская по изготовлению музыкальных инструментов для Нового Света.</Text>
        </Text>
        <Text>
            <GUID>1742110051</GUID>            <!--  Music Hall: Blank - Building -->
            <Text>Концертный зал: Пусто</Text>
        </Text>
        <Text>
            <GUID>1742110052</GUID>            <!--  Music Hall: Blank - Building - Description -->
            <Text>Дайте потрясающие концерты, где будут играть на этих изумительных инструментах! Выберите концерт.</Text>
        </Text>
        <Text>
            <GUID>1742110053</GUID>            <!--  Music Hall: Epic Sax - Building -->
            <Text>Концертный зал: Эпичный саксофон</Text>
        </Text>
        <Text>
            <GUID>1742110054</GUID>            <!--  Music Hall: Epic Sax - Building - Description -->
            <Text>Начните особый концерт, где будут играть на этих новомодных саксофонах! "Эпичные звуки саксофона"</Text>
        </Text>
        <Text>
            <GUID>1742110055</GUID>            <!--  Music Hall: Common Sounds - Building -->
            <Text>Концертный зал: Простой концерт</Text>
        </Text>
        <Text>
            <GUID>1742110056</GUID>            <!--  Music Hall: Common Sounds - Building - Description -->
            <Text>Проведите очередной концерт, где будут играть наши выпускники на своих музыкальных инструментах! Простой концерт.</Text>
        </Text>
        <Text>
            <GUID>1742110057</GUID>            <!--  Music Hall: Epic Sounds - Building -->
            <Text>Концертный зал: Расширенный концерт</Text>
        </Text>
        <Text>
            <GUID>1742110058</GUID>            <!--  Music Hall: Epic Sounds - Building - Description -->
            <Text>Дайте интересный концерт, где местные музыканты смогут показать игру на всех этих изумительных инструментах! Расширенный концерт.</Text>
        </Text>
        <Text>
            <GUID>1742110059</GUID>            <!--  Music Hall: Legendary Sounds - Building -->
            <Text>Концертный зал: Грандиозный концерт</Text>
        </Text>
        <Text>
            <GUID>1742110060</GUID>            <!--  Music Hall: Legendary Sounds - Building - Description -->
            <Text>Настало время дать по-настоящему потрясающий концерт, где будут играть приглашённые музыкальные таланты на лучших и уникальных инструментах! Грандиозный концерт!</Text>
        </Text>
        <Text>
            <GUID>1742110061</GUID>            <!--  Music Hall - RecipeList -->
            <Text>Концертный зал</Text>
        </Text>
        <Text>
            <GUID>1742110062</GUID>            <!-- Music Hall - RecipeList - Description -->
            <Text>Дайте потрясающие концерты, где будут играть на различных музыкальных инструментах! Выберите подходящий концерт.</Text>
        </Text>
        <Text>
            <GUID>1742110063</GUID>            <!--  Music Hall: Epic Sax - Recipe -->
            <Text>Эпичный саксофон</Text>
        </Text>
        <Text>
            <GUID>1742110064</GUID>            <!--  Music Hall: Epic Sax - Recipe - Description -->
            <Text>Начните особый концерт, где будут играть на этих новомодных саксофонах! "Эпичные звуки саксофона"</Text>
        </Text>
        <Text>
            <GUID>1742110065</GUID>            <!--  Music Hall: Common Sounds - Recipe -->
            <Text>Простой концерт</Text>
        </Text>
        <Text>
            <GUID>1742110066</GUID>            <!--  Music Hall: Common Sounds - Recipe - Description -->
            <Text>Проведите очередной концерт, где будут играть наши выпускники на своих музыкальных инструментах! Простой концерт.</Text>
        </Text>
        <Text>
            <GUID>1742110067</GUID>            <!--  Music Hall: Epic Sounds - Recipe -->
            <Text>Расширенный концерт</Text>
        </Text>
        <Text>
            <GUID>1742110068</GUID>            <!--  Music Hall: Epic Sounds - Recipe - Description -->
            <Text>Дайте интересный концерт, где местные музыканты смогут показать игру на всех этих изумительных инструментах! Расширенный концерт.</Text>
        </Text>
        <Text>
            <GUID>1742110069</GUID>            <!--  Music Hall: Legendary Sounds - Recipe -->
            <Text>Грандиозный концерт</Text>
        </Text>
        <Text>
            <GUID>1742110070</GUID>            <!--  Music Hall: Legendary Sounds - Recipe - Description -->
            <Text>Настало время дать по-настоящему потрясающий концерт, где будут играть приглашённые музыкальные таланты на лучших и уникальных инструментах! Грандиозный концерт!</Text>
        </Text>
        <Text>
            <GUID>1742110071</GUID>            <!--  Music Hall - Product -->
            <Text>Концертный зал</Text>
        </Text>
        <Text>
            <GUID>1742110072</GUID>            <!-- Music Hall - Product - Description -->
            <Text>Дайте потрясающие концерты, где будут играть на этих изумительных инструментах!</Text>
        </Text>
        <Text>
            <GUID>1742110073</GUID>            <!--  Epic Sax - TownhallBuff -->
            <Text>Эпический саксофон</Text>
        </Text>
        <Text>
            <GUID>1742110074</GUID>            <!-- Epic Sax - TownhallBuff - Description -->
            <Text>Определённо эпическое выступление на саксофоне, которое вы когда-либо слышали.</Text>
        </Text>
        <Text>
            <GUID>1742110075</GUID>            <!--  Common Sounds - TownhallBuff -->
            <Text>Обычный концерт</Text>
        </Text>
        <Text>
            <GUID>1742110076</GUID>            <!-- Common Sounds - TownhallBuff - Description -->
            <Text>Вполне распространённый репертуар, который вы обычно слушаете.</Text>
        </Text>
        <Text>
            <GUID>1742110077</GUID>            <!--  Epic Sounds - TownhallBuff -->
            <Text>Расширенный концерт</Text>
        </Text>
        <Text>
            <GUID>1742110078</GUID>            <!-- Epic Sounds - TownhallBuff - Description -->
            <Text>Довольно интересная музыкальная программа, среди тех, что вы слышали.</Text>
        </Text>
        <Text>
            <GUID>1742110079</GUID>            <!--  Legendary Sounds - TownhallBuff -->
            <Text>Грандиозный концерт</Text>
        </Text>
        <Text>
            <GUID>1742110080</GUID>            <!-- Legendary Sounds - TownhallBuff - Description -->
            <Text>Поистине легендарное и наиболее впечатляющее музыкальное произведение, которое вы когда-либо слышали!</Text>
        </Text>
        <Text>
            <GUID>1742110081</GUID>            <!--  Antoine-Joseph Sax, Inventor of the Saxophone - GuildhouseItem -->
            <Text>Антуан-Жозеф Сакс, Изобретатель саксофона</Text>
        </Text>
        <Text>
            <GUID>1742110082</GUID>            <!-- Antoine-Joseph Sax, Inventor of the Saxophone - GuildhouseItem - Description -->
            <Text>Также известный как Адольф, он изобрел саксофон и дал своё имя этому изумительному инструменту. Когда он принялся за изготовление саксофона, Сакс жаждал создать инструмент, который мог бы сочетать в себе оркестровые звуки деревянных духовых инструментов, а также медных инструментов. Его изобретение должно было иметь качество тона деревянного духового инструмента и силу латуни. Также Сакс наладил прекрасный способ производства саксофона с учетом техники безопасности.</Text>
        </Text>
        <Text>
            <GUID>1742110086</GUID>            <!--  Saxophone - ProductionChain -->
            <Text>Саксофон</Text>
        </Text>
        <Text>
            <GUID>1742110087</GUID>            <!-- Saxophone - ProductionChain - Description -->
            <Text>Саксофон - это единственный в мире инструмент, производящийся из изогнутой латуни. Типичный саксофон изготавливается в 8 вариантах - сопраниссимо, сопранино, сопрано, альт, тенор, баритон, бас и контрабас. Саксофон можно разделить на 3 главных элемента: корпус, раструб, тонкая трубка, на которую насаживается мундштук, являющийся малой частью инструмента. Основные этапы производства включают в себя формирование деталей, их сборку и окончательную полировку.</Text>
        </Text>
        <Text>
            <GUID>1742110088</GUID>            <!--  Harp - ProductionChain -->
            <Text>Арфа</Text>
        </Text>
        <Text>
            <GUID>1742110089</GUID>            <!-- Harp - ProductionChain - Description -->
            <Text>В производстве арфы всё начинается с древесины, которая отстаивается годами. Затем идёт склейка, обточка и сборка. Собирается каркас корпуса, обшивка, после чего начинается подгонка. С одной стороны – всё делается по чертежам, строгим нормативам, а с другой - каждый инструмент индивидуален и звучит по-своему. Это ремесло, где ничего не повторяется и двух одинаковых арф нет. Скоро эти заготовки станут роскошными арфами!</Text>
        </Text>
        <Text>
            <GUID>1742110090</GUID>            <!--  Piano - ProductionChain -->
            <Text>Фортепиано</Text>
        </Text>
        <Text>
            <GUID>1742110091</GUID>            <!-- Piano - ProductionChain - Description -->
            <Text>Дерево, которое звучит! Нет ни одного инструмента, который в истории музыки имел бы настолько сильное влияние на целые эпохи, как фортепиано. Сорта твердой древесины используют для изготовления футора (остов корпуса), вирбельбанка (колковой доски), постелей дек, и различных частей механики. Упругие и эластичные сорта древесины используются для изготовления резонансных дек, клавиш, штульрам и клавиатурных рам. Чугунная рама - важнейшая составная часть, выдерживающая на себе суммарное натяжение струн, которое может превышать 20 тонн. В сложнейшем процессе создания фортепиано используются до 12 000 частей и деталей!</Text>
        </Text>
        <Text>
            <GUID>1742110092</GUID>            <!--  Guitar - ProductionChain -->
            <Text>Гитары</Text>
        </Text>
        <Text>
            <GUID>1742110093</GUID>            <!-- Guitar - ProductionChain - Description -->
            <Text>Здесь используется шпон только самого высокого качества! Древесина с сучками и трещинками сразу отбраковываются. Происходит просушка, потом кроят верхнюю и нижнюю деки и прессуют шпон в блок для последующего изготовления гитарного грифа. Далее блок разрезают, собирают и шлифуют и лакируют. После чего всё соединят вместе, устанавливают колковый механизм и натягивают струны.</Text>
        </Text>
        <Text>
            <GUID>1742110094</GUID>            <!--  Banjo - ProductionChain -->
            <Text>Банджо</Text>
        </Text>
        <Text>
            <GUID>1742110095</GUID>            <!-- Banjo - ProductionChain - Description -->
            <Text>Банджо - задорный инструмент, сделанный  из деревянного шпона и стали, который раньше делали из высушенной тыквы с натянутой на неё кожей. Из инструмента льётся яркая и звонкая музыка с четким, заводным ритмом.</Text>
        </Text>
        <Text>
            <GUID>1742110096</GUID>            <!--  Mahaya - Trader Name -->
            <Text>Махайя Мюзик</Text>
        </Text>
        <Text>
            <GUID>1742110097</GUID>            <!-- Mahaya - Trader Name - Description -->
            <Text>Всемирно известный производитель музыкальных инструментов.</Text>
        </Text>
        <Text>
            <GUID>1742110100</GUID>            <!--  Artisan's Workshop: Flute - Building -->
            <Text>Мастерская ремесленника: Флейта</Text>
        </Text>
        <Text>
            <GUID>1742110102</GUID>            <!--  Flute - Recipe -->
            <Text>Флейта</Text>
        </Text>
        <Text>
            <GUID>1742110103</GUID>            <!-- Flute - Recipe - Description -->
            <Text>Процесс изготовления каждой флейты - это целый жизненный цикл, каждый из этапов которого очень важен и уникален. Для достижения наивысшего качества продукции каждому этапу изготовления уделяется максимальное внимание, а весь цикл работ выполняется вручную, с контролем всех тонкостей создания качественного музыкального инструмента.</Text>
        </Text>
        <Text>
            <GUID>1742110104</GUID>            <!--  Flute - ProductionChain -->
            <Text>Флейта</Text>
        </Text>
        <Text>
            <GUID>1742110111</GUID>            <!-- Clown Fizboo, Street Performer - TownhallItem -->
            <Text>Клоун Физбу, уличный артист</Text>
        </Text>
        <Text>
            <GUID>1742110112</GUID>            <!-- Clown Fizboo, Street Performer - TownhallItem - Description -->
            <Text>Клоуна Физбу часто сравнивают с его придурковатым братом. Но позвольте ему немного одурачить вас! Ведь его выступление просто поражает. Для этого клоуна не скроется ни один секрет в музыке или фокусных представлениях.</Text>
        </Text>
        <Text>
            <GUID>1742110113</GUID>            <!--  Giorgio Pirazzi, Theory of strings - GuildhouseItem -->
            <Text>Джорджио Пирацци, «Теория струн»</Text>
        </Text>
        <Text>
            <GUID>1742110114</GUID>            <!-- Giorgio Pirazzi, Theory of strings - GuildhouseItem - Description -->
            <Text>Струнные инструменты развивались с течением времени. Это касается и самих струн. Струны прошли долгий путь, а вместе с ними менялись не только материалы, но и способы их изготовления. Джорджио построил семейный бизнес на производстве новых видов струн для музыкальных инструментов. Он помогает другим фабрикам адаптировать новаторские процессы для производства струн.</Text>
        </Text>
        <!-- EXTRA FOR SHARED GOODS-->
        <Text>
            <GUID>1742110083</GUID>            <!-- Trader Goods  - Infotip Message -->
            <Text>Торговец товарами</Text>
        </Text>
        <Text>
            <GUID>1742110084</GUID>            <!-- Trader Goods  - Infotip Message - Description -->
            <Text>Вы не можете производить этот товар. Купите его у торговцев:</Text>
        </Text>
        <Text>
            <GUID>1742110085</GUID>            <!-- Trader Goods  - Infotip -->
            <Text>Струны для классических инструментов</Text>
        </Text>
        <Text>
            <GUID>1440231</GUID>            <!-- Strings  - Product -->
            <Text>Струны</Text>
        </Text>
    </ModOp>
</ModOps>